[
  {
    "text": "remove the water",
    "entities": [
      {
        "start": 11,
        "end": 16,
        "value": "water",
        "entity": "item"
      }
    ],
    "predicted_entities": []
  },
  {
    "text": "can you please remove chips?",
    "entities": [
      {
        "start": 22,
        "end": 27,
        "value": "chips",
        "entity": "item"
      }
    ],
    "predicted_entities": []
  },
  {
    "text": "hi Mister",
    "entities": [],
    "predicted_entities": [
      {
        "entity": "user",
        "start": 3,
        "end": 9,
        "confidence_entity": 0.9996603727340698,
        "value": "Mister",
        "extractor": "DIETClassifier"
      }
    ]
  },
  {
    "text": "add six cans of lentils",
    "entities": [
      {
        "start": 4,
        "end": 7,
        "value": "6",
        "entity": "quantity"
      },
      {
        "start": 8,
        "end": 12,
        "value": "can",
        "entity": "uom"
      },
      {
        "start": 16,
        "end": 23,
        "value": "lentils",
        "entity": "item"
      }
    ],
    "predicted_entities": [
      {
        "entity": "quantity",
        "start": 4,
        "end": 7,
        "confidence_entity": 0.9998452663421631,
        "value": "6",
        "extractor": "DIETClassifier",
        "processors": [
          "EntitySynonymMapper"
        ]
      },
      {
        "entity": "uom",
        "start": 8,
        "end": 12,
        "confidence_entity": 0.9320230484008789,
        "value": "can",
        "extractor": "DIETClassifier",
        "processors": [
          "EntitySynonymMapper"
        ]
      },
      {
        "entity": "uom",
        "start": 16,
        "end": 23,
        "confidence_entity": 0.621230959892273,
        "value": "lentils",
        "extractor": "DIETClassifier"
      }
    ]
  },
  {
    "text": "can u pls add [2] disinfectant cleaner",
    "entities": [
      {
        "start": 18,
        "end": 38,
        "value": "disinfectant cleaner",
        "entity": "item"
      }
    ],
    "predicted_entities": [
      {
        "entity": "quantity",
        "start": 14,
        "end": 16,
        "confidence_entity": 0.9999716281890869,
        "value": "[2",
        "extractor": "DIETClassifier"
      },
      {
        "entity": "item",
        "start": 18,
        "end": 38,
        "confidence_entity": 0.9998180270195007,
        "value": "disinfectant cleaner",
        "extractor": "DIETClassifier"
      }
    ]
  },
  {
    "text": "garlic",
    "entities": [
      {
        "start": 0,
        "end": 6,
        "value": "garlic",
        "entity": "item"
      }
    ],
    "predicted_entities": [
      {
        "entity": "user",
        "start": 0,
        "end": 6,
        "confidence_entity": 0.9926490187644958,
        "value": "garlic",
        "extractor": "DIETClassifier"
      }
    ]
  },
  {
    "text": "mussel",
    "entities": [
      {
        "start": 0,
        "end": 6,
        "value": "mussel",
        "entity": "item"
      }
    ],
    "predicted_entities": []
  },
  {
    "text": "lentils",
    "entities": [
      {
        "start": 0,
        "end": 7,
        "value": "lentils",
        "entity": "item"
      }
    ],
    "predicted_entities": [
      {
        "entity": "user",
        "start": 0,
        "end": 7,
        "confidence_entity": 0.9053807258605957,
        "value": "lentils",
        "extractor": "DIETClassifier"
      }
    ]
  },
  {
    "text": "eight",
    "entities": [
      {
        "start": 0,
        "end": 5,
        "value": "eight",
        "entity": "quantity"
      }
    ],
    "predicted_entities": []
  },
  {
    "text": "lobster",
    "entities": [
      {
        "start": 0,
        "end": 7,
        "value": "lobster",
        "entity": "item"
      }
    ],
    "predicted_entities": []
  },
  {
    "text": "avocado",
    "entities": [
      {
        "start": 0,
        "end": 7,
        "value": "avocado",
        "entity": "item"
      }
    ],
    "predicted_entities": []
  }
]