[
  {
    "text": "i'm off",
    "intent": "goodbye",
    "intent_prediction": {
      "name": "greet",
      "confidence": 0.44103651805911886
    }
  },
  {
    "text": "see you",
    "intent": "goodbye",
    "intent_prediction": {
      "name": "show",
      "confidence": 0.4682557717795661
    }
  },
  {
    "text": "bye bot",
    "intent": "goodbye",
    "intent_prediction": {
      "name": "greet",
      "confidence": 0.3584309405189608
    }
  },
  {
    "text": "insert three bottle of toilet gel",
    "intent": "insert",
    "intent_prediction": {
      "name": "inform",
      "confidence": 0.7920582091251164
    }
  },
  {
    "text": "2 bottle of extra virgin olive oil",
    "intent": "insert",
    "intent_prediction": {
      "name": "inform",
      "confidence": 0.7102544980905265
    }
  },
  {
    "text": "a quarter",
    "intent": "inform",
    "intent_prediction": {
      "name": "insert",
      "confidence": 0.4624897165795304
    }
  },
  {
    "text": "can",
    "intent": "inform",
    "intent_prediction": {
      "name": "insert",
      "confidence": 0.48066172808134744
    }
  }
]