[
  {
    "text": "logou",
    "entities": [],
    "predicted_entities": [
      {
        "entity": "user",
        "start": 0,
        "end": 5,
        "confidence_entity": 0.4716914755062287,
        "value": "logou",
        "extractor": "CRFEntityExtractor"
      }
    ]
  },
  {
    "text": "do you have something else",
    "entities": [],
    "predicted_entities": [
      {
        "entity": "item",
        "start": 22,
        "end": 26,
        "confidence_entity": 0.437790490329049,
        "value": "else",
        "extractor": "CRFEntityExtractor"
      }
    ]
  },
  {
    "text": "empty",
    "entities": [],
    "predicted_entities": [
      {
        "entity": "user",
        "start": 0,
        "end": 5,
        "confidence_entity": 0.5151746974783626,
        "value": "empty",
        "extractor": "CRFEntityExtractor"
      }
    ]
  },
  {
    "text": "goodnight",
    "entities": [],
    "predicted_entities": [
      {
        "entity": "user",
        "start": 0,
        "end": 9,
        "confidence_entity": 0.46239791520736967,
        "value": "goodnight",
        "extractor": "CRFEntityExtractor"
      }
    ]
  },
  {
    "text": "can you delete tomatoes?",
    "entities": [
      {
        "start": 15,
        "end": 23,
        "value": "tomatoes",
        "entity": "item"
      }
    ],
    "predicted_entities": []
  },
  {
    "text": "delete the bread",
    "entities": [
      {
        "start": 11,
        "end": 16,
        "value": "bread",
        "entity": "item"
      }
    ],
    "predicted_entities": []
  },
  {
    "text": "can you please remove pepper?",
    "entities": [
      {
        "start": 22,
        "end": 28,
        "value": "pepper",
        "entity": "item"
      }
    ],
    "predicted_entities": []
  },
  {
    "text": "can you delete the strawberry?",
    "entities": [
      {
        "start": 19,
        "end": 29,
        "value": "strawberry",
        "entity": "item"
      }
    ],
    "predicted_entities": []
  },
  {
    "text": "can you delete the cherry?",
    "entities": [
      {
        "start": 19,
        "end": 25,
        "value": "cherry",
        "entity": "item"
      }
    ],
    "predicted_entities": []
  },
  {
    "text": "hey bot",
    "entities": [],
    "predicted_entities": [
      {
        "entity": "item",
        "start": 4,
        "end": 7,
        "confidence_entity": 0.39141800121776915,
        "value": "bot",
        "extractor": "CRFEntityExtractor"
      }
    ]
  },
  {
    "text": "my name is Ernest",
    "entities": [
      {
        "start": 11,
        "end": 17,
        "value": "Ernest",
        "entity": "user"
      }
    ],
    "predicted_entities": []
  },
  {
    "text": "hi bot",
    "entities": [],
    "predicted_entities": [
      {
        "entity": "item",
        "start": 3,
        "end": 6,
        "confidence_entity": 0.4472897559443866,
        "value": "bot",
        "extractor": "CRFEntityExtractor"
      }
    ]
  },
  {
    "text": "can u add 1 bottle of body scrub?",
    "entities": [
      {
        "start": 10,
        "end": 11,
        "value": "1",
        "entity": "quantity"
      },
      {
        "start": 12,
        "end": 18,
        "value": "bottle",
        "entity": "uom"
      },
      {
        "start": 22,
        "end": 32,
        "value": "body scrub",
        "entity": "item"
      }
    ],
    "predicted_entities": [
      {
        "entity": "quantity",
        "start": 10,
        "end": 11,
        "confidence_entity": 0.9610475402444227,
        "value": "1",
        "extractor": "CRFEntityExtractor"
      },
      {
        "entity": "uom",
        "start": 12,
        "end": 18,
        "confidence_entity": 0.9833853838308856,
        "value": "bottle",
        "extractor": "CRFEntityExtractor"
      }
    ]
  },
  {
    "text": "insert 1 carpet cleaner",
    "entities": [
      {
        "start": 7,
        "end": 8,
        "value": "1",
        "entity": "quantity"
      },
      {
        "start": 9,
        "end": 23,
        "value": "carpet cleaner",
        "entity": "item"
      }
    ],
    "predicted_entities": [
      {
        "entity": "item",
        "start": 9,
        "end": 23,
        "confidence_entity": 0.6362692609457589,
        "value": "carpet cleaner",
        "extractor": "CRFEntityExtractor"
      }
    ]
  },
  {
    "text": "can u add a dozen egg",
    "entities": [
      {
        "start": 10,
        "end": 17,
        "value": "12",
        "entity": "quantity"
      },
      {
        "start": 18,
        "end": 21,
        "value": "egg",
        "entity": "item"
      }
    ],
    "predicted_entities": [
      {
        "entity": "quantity",
        "start": 10,
        "end": 11,
        "confidence_entity": 0.569614019418401,
        "value": "1",
        "extractor": "CRFEntityExtractor",
        "processors": [
          "EntitySynonymMapper"
        ]
      },
      {
        "entity": "item",
        "start": 18,
        "end": 21,
        "confidence_entity": 0.5290219524949762,
        "value": "egg",
        "extractor": "CRFEntityExtractor"
      }
    ]
  },
  {
    "text": "insert sugar",
    "entities": [
      {
        "start": 7,
        "end": 12,
        "value": "sugar",
        "entity": "item"
      }
    ],
    "predicted_entities": []
  },
  {
    "text": "can u pls add 1 melon?",
    "entities": [
      {
        "start": 14,
        "end": 15,
        "value": "1",
        "entity": "quantity"
      },
      {
        "start": 16,
        "end": 21,
        "value": "melon",
        "entity": "item"
      }
    ],
    "predicted_entities": []
  },
  {
    "text": "can u pls add three kilos of peach?",
    "entities": [
      {
        "start": 14,
        "end": 19,
        "value": "3",
        "entity": "quantity"
      },
      {
        "start": 20,
        "end": 25,
        "value": "kilogram",
        "entity": "uom"
      },
      {
        "start": 29,
        "end": 34,
        "value": "peach",
        "entity": "item"
      }
    ],
    "predicted_entities": []
  },
  {
    "text": "add six cans of lentils",
    "entities": [
      {
        "start": 4,
        "end": 7,
        "value": "6",
        "entity": "quantity"
      },
      {
        "start": 8,
        "end": 12,
        "value": "can",
        "entity": "uom"
      },
      {
        "start": 16,
        "end": 23,
        "value": "lentils",
        "entity": "item"
      }
    ],
    "predicted_entities": [
      {
        "entity": "item",
        "start": 16,
        "end": 23,
        "confidence_entity": 0.5812666057445086,
        "value": "lentils",
        "extractor": "CRFEntityExtractor"
      }
    ]
  },
  {
    "text": "write down 1/4 kilos of baking soda",
    "entities": [
      {
        "start": 11,
        "end": 14,
        "value": "0.25",
        "entity": "quantity"
      },
      {
        "start": 15,
        "end": 20,
        "value": "kilogram",
        "entity": "uom"
      },
      {
        "start": 24,
        "end": 35,
        "value": "baking soda",
        "entity": "item"
      }
    ],
    "predicted_entities": [
      {
        "entity": "item",
        "start": 24,
        "end": 35,
        "confidence_entity": 0.9439162543813022,
        "value": "baking soda",
        "extractor": "CRFEntityExtractor"
      }
    ]
  },
  {
    "text": "write down 1 marmellade jar",
    "entities": [
      {
        "start": 11,
        "end": 12,
        "value": "1",
        "entity": "quantity"
      },
      {
        "start": 13,
        "end": 23,
        "value": "jam",
        "entity": "item"
      },
      {
        "start": 24,
        "end": 27,
        "value": "jar",
        "entity": "uom"
      }
    ],
    "predicted_entities": [
      {
        "entity": "user",
        "start": 24,
        "end": 27,
        "confidence_entity": 0.3566585677471375,
        "value": "jar",
        "extractor": "CRFEntityExtractor"
      }
    ]
  },
  {
    "text": "i need one pack of dental floss",
    "entities": [
      {
        "start": 7,
        "end": 10,
        "value": "1",
        "entity": "quantity"
      },
      {
        "start": 11,
        "end": 15,
        "value": "pack",
        "entity": "uom"
      },
      {
        "start": 19,
        "end": 31,
        "value": "dental floss",
        "entity": "item"
      }
    ],
    "predicted_entities": [
      {
        "entity": "quantity",
        "start": 7,
        "end": 10,
        "confidence_entity": 0.9791234694273087,
        "value": "1",
        "extractor": "CRFEntityExtractor",
        "processors": [
          "EntitySynonymMapper"
        ]
      },
      {
        "entity": "uom",
        "start": 11,
        "end": 15,
        "confidence_entity": 0.8799702995881971,
        "value": "pack",
        "extractor": "CRFEntityExtractor"
      },
      {
        "entity": "item",
        "start": 26,
        "end": 31,
        "confidence_entity": 0.8549689205785599,
        "value": "dental floss",
        "extractor": "CRFEntityExtractor",
        "processors": [
          "EntitySynonymMapper"
        ]
      }
    ]
  },
  {
    "text": "mark 0.5 kilogram of bread",
    "entities": [
      {
        "start": 5,
        "end": 8,
        "value": "0.5",
        "entity": "quantity"
      },
      {
        "start": 9,
        "end": 17,
        "value": "kilogram",
        "entity": "uom"
      },
      {
        "start": 21,
        "end": 26,
        "value": "bread",
        "entity": "item"
      }
    ],
    "predicted_entities": [
      {
        "entity": "uom",
        "start": 9,
        "end": 17,
        "confidence_entity": 0.7743733940734072,
        "value": "kilogram",
        "extractor": "CRFEntityExtractor"
      },
      {
        "entity": "item",
        "start": 21,
        "end": 26,
        "confidence_entity": 0.5460883949365588,
        "value": "bread",
        "extractor": "CRFEntityExtractor"
      }
    ]
  },
  {
    "text": "paprika",
    "entities": [
      {
        "start": 0,
        "end": 7,
        "value": "paprika",
        "entity": "item"
      }
    ],
    "predicted_entities": [
      {
        "entity": "user",
        "start": 0,
        "end": 7,
        "confidence_entity": 0.504263248792646,
        "value": "paprika",
        "extractor": "CRFEntityExtractor"
      }
    ]
  },
  {
    "text": "toothpaste",
    "entities": [
      {
        "start": 0,
        "end": 10,
        "value": "toothpaste",
        "entity": "item"
      }
    ],
    "predicted_entities": [
      {
        "entity": "user",
        "start": 0,
        "end": 10,
        "confidence_entity": 0.4764560605746611,
        "value": "toothpaste",
        "extractor": "CRFEntityExtractor"
      }
    ]
  },
  {
    "text": "barbeque sauce",
    "entities": [
      {
        "start": 0,
        "end": 14,
        "value": "barbeque sauce",
        "entity": "item"
      }
    ],
    "predicted_entities": []
  },
  {
    "text": "prawn",
    "entities": [
      {
        "start": 0,
        "end": 5,
        "value": "prawn",
        "entity": "item"
      }
    ],
    "predicted_entities": [
      {
        "entity": "user",
        "start": 0,
        "end": 5,
        "confidence_entity": 0.544259205971928,
        "value": "prawn",
        "extractor": "CRFEntityExtractor"
      }
    ]
  },
  {
    "text": "green beans",
    "entities": [
      {
        "start": 0,
        "end": 11,
        "value": "green beans",
        "entity": "item"
      }
    ],
    "predicted_entities": [
      {
        "entity": "user",
        "start": 6,
        "end": 11,
        "confidence_entity": 0.3323671085334009,
        "value": "beans",
        "extractor": "CRFEntityExtractor"
      }
    ]
  },
  {
    "text": "pumpkin",
    "entities": [
      {
        "start": 0,
        "end": 7,
        "value": "pumpkin",
        "entity": "item"
      }
    ],
    "predicted_entities": [
      {
        "entity": "user",
        "start": 0,
        "end": 7,
        "confidence_entity": 0.5784557720273408,
        "value": "pumpkin",
        "extractor": "CRFEntityExtractor"
      }
    ]
  },
  {
    "text": "yogurt",
    "entities": [
      {
        "start": 0,
        "end": 6,
        "value": "yogurt",
        "entity": "item"
      }
    ],
    "predicted_entities": [
      {
        "entity": "user",
        "start": 0,
        "end": 6,
        "confidence_entity": 0.5334941503588327,
        "value": "yogurt",
        "extractor": "CRFEntityExtractor"
      }
    ]
  },
  {
    "text": "prosciutto",
    "entities": [
      {
        "start": 0,
        "end": 10,
        "value": "prosciutto",
        "entity": "item"
      }
    ],
    "predicted_entities": [
      {
        "entity": "user",
        "start": 0,
        "end": 10,
        "confidence_entity": 0.4253921400229327,
        "value": "prosciutto",
        "extractor": "CRFEntityExtractor"
      }
    ]
  },
  {
    "text": "ketchup",
    "entities": [
      {
        "start": 0,
        "end": 7,
        "value": "ketchup",
        "entity": "item"
      }
    ],
    "predicted_entities": [
      {
        "entity": "user",
        "start": 0,
        "end": 7,
        "confidence_entity": 0.5486954637120749,
        "value": "ketchup",
        "extractor": "CRFEntityExtractor"
      }
    ]
  },
  {
    "text": "cherry",
    "entities": [
      {
        "start": 0,
        "end": 6,
        "value": "cherry",
        "entity": "item"
      }
    ],
    "predicted_entities": [
      {
        "entity": "user",
        "start": 0,
        "end": 6,
        "confidence_entity": 0.3834344962039001,
        "value": "cherry",
        "extractor": "CRFEntityExtractor"
      }
    ]
  },
  {
    "text": "crab",
    "entities": [
      {
        "start": 0,
        "end": 4,
        "value": "crab",
        "entity": "item"
      }
    ],
    "predicted_entities": [
      {
        "entity": "user",
        "start": 0,
        "end": 4,
        "confidence_entity": 0.4927960669520323,
        "value": "crab",
        "extractor": "CRFEntityExtractor"
      }
    ]
  },
  {
    "text": "bacon",
    "entities": [
      {
        "start": 0,
        "end": 5,
        "value": "bacon",
        "entity": "item"
      }
    ],
    "predicted_entities": [
      {
        "entity": "user",
        "start": 0,
        "end": 5,
        "confidence_entity": 0.5465689703327984,
        "value": "bacon",
        "extractor": "CRFEntityExtractor"
      }
    ]
  },
  {
    "text": "nine",
    "entities": [
      {
        "start": 0,
        "end": 4,
        "value": "nine",
        "entity": "quantity"
      }
    ],
    "predicted_entities": [
      {
        "entity": "user",
        "start": 0,
        "end": 4,
        "confidence_entity": 0.7786727406960797,
        "value": "9",
        "extractor": "CRFEntityExtractor",
        "processors": [
          "EntitySynonymMapper"
        ]
      }
    ]
  },
  {
    "text": "jar",
    "entities": [
      {
        "start": 0,
        "end": 3,
        "value": "jar",
        "entity": "uom"
      }
    ],
    "predicted_entities": [
      {
        "entity": "user",
        "start": 0,
        "end": 3,
        "confidence_entity": 0.7227299138504522,
        "value": "jar",
        "extractor": "CRFEntityExtractor"
      }
    ]
  },
  {
    "text": "bread",
    "entities": [
      {
        "start": 0,
        "end": 5,
        "value": "bread",
        "entity": "item"
      }
    ],
    "predicted_entities": [
      {
        "entity": "user",
        "start": 0,
        "end": 5,
        "confidence_entity": 0.5335695040922661,
        "value": "bread",
        "extractor": "CRFEntityExtractor"
      }
    ]
  },
  {
    "text": "melon",
    "entities": [
      {
        "start": 0,
        "end": 5,
        "value": "melon",
        "entity": "item"
      }
    ],
    "predicted_entities": [
      {
        "entity": "user",
        "start": 0,
        "end": 5,
        "confidence_entity": 0.6091538979435694,
        "value": "melon",
        "extractor": "CRFEntityExtractor"
      }
    ]
  },
  {
    "text": "nut",
    "entities": [
      {
        "start": 0,
        "end": 3,
        "value": "nut",
        "entity": "item"
      }
    ],
    "predicted_entities": [
      {
        "entity": "user",
        "start": 0,
        "end": 3,
        "confidence_entity": 0.5351997256699753,
        "value": "nut",
        "extractor": "CRFEntityExtractor"
      }
    ]
  },
  {
    "text": "two",
    "entities": [
      {
        "start": 0,
        "end": 3,
        "value": "two",
        "entity": "quantity"
      }
    ],
    "predicted_entities": [
      {
        "entity": "user",
        "start": 0,
        "end": 3,
        "confidence_entity": 0.5231274352066762,
        "value": "2",
        "extractor": "CRFEntityExtractor",
        "processors": [
          "EntitySynonymMapper"
        ]
      }
    ]
  },
  {
    "text": "chicken",
    "entities": [
      {
        "start": 0,
        "end": 7,
        "value": "chicken",
        "entity": "item"
      }
    ],
    "predicted_entities": [
      {
        "entity": "user",
        "start": 0,
        "end": 7,
        "confidence_entity": 0.49328240229195547,
        "value": "chicken",
        "extractor": "CRFEntityExtractor"
      }
    ]
  },
  {
    "text": "deny",
    "entities": [
      {
        "start": 0,
        "end": 4,
        "value": "deny",
        "entity": "yes_no_answer"
      }
    ],
    "predicted_entities": [
      {
        "entity": "user",
        "start": 0,
        "end": 4,
        "confidence_entity": 0.48313405093071,
        "value": "deny",
        "extractor": "CRFEntityExtractor"
      }
    ]
  },
  {
    "text": "beer",
    "entities": [
      {
        "start": 0,
        "end": 4,
        "value": "beer",
        "entity": "item"
      }
    ],
    "predicted_entities": [
      {
        "entity": "user",
        "start": 0,
        "end": 4,
        "confidence_entity": 0.6026450524324943,
        "value": "beer",
        "extractor": "CRFEntityExtractor"
      }
    ]
  },
  {
    "text": "seven",
    "entities": [
      {
        "start": 0,
        "end": 5,
        "value": "seven",
        "entity": "quantity"
      }
    ],
    "predicted_entities": [
      {
        "entity": "user",
        "start": 0,
        "end": 5,
        "confidence_entity": 0.5155520708841836,
        "value": "7",
        "extractor": "CRFEntityExtractor",
        "processors": [
          "EntitySynonymMapper"
        ]
      }
    ]
  },
  {
    "text": "lamb",
    "entities": [
      {
        "start": 0,
        "end": 4,
        "value": "lamb",
        "entity": "item"
      }
    ],
    "predicted_entities": [
      {
        "entity": "user",
        "start": 0,
        "end": 4,
        "confidence_entity": 0.507401315316291,
        "value": "lamb",
        "extractor": "CRFEntityExtractor"
      }
    ]
  }
]